pybalmorel/__init__.py
pybalmorel/functions.py
pybalmorel-0.0.13.dist-info/LICENSE
pybalmorel-0.0.13.dist-info/METADATA
pybalmorel-0.0.13.dist-info/WHEEL
pybalmorel-0.0.13.dist-info/top_level.txt
pybalmorel-0.0.13.dist-info/RECORD
