Metadata-Version: 2.1
Name: pybalmorel
Version: 0.0.13
Summary: A package for convenient python functions when processing Balmorel data or results
Author-email: Mathias Berg Rosendal <mathiasros@gmail.com>
Project-URL: Homepage, https://github.com/Mathias157
Project-URL: Issues, https://github.com/Mathias157/balmorel-preprocessing/issues
Classifier: Programming Language :: Python :: 3
Classifier: License :: OSI Approved :: MIT License
Classifier: Operating System :: OS Independent
Requires-Python: >=3.9
License-File: LICENSE
